hwp/__init__.py
hwp/enums.py
hwp/hwpfile.py
hwp/utils.py
hwp_py-0.0.2.dist-info/LICENSE
hwp_py-0.0.2.dist-info/METADATA
hwp_py-0.0.2.dist-info/WHEEL
hwp_py-0.0.2.dist-info/top_level.txt
hwp_py-0.0.2.dist-info/RECORD
