Metadata-Version: 2.1
Name: hwp-py
Version: 0.0.2
Summary: UNKNOWN
Home-page: https://github.com/hallazzang/hwp-py
Author: Hanjun Kim
Author-email: hallazzang@gmail.com
License: MIT
Platform: UNKNOWN
Classifier: License :: OSI Approved :: MIT License
Classifier: Programming Language :: Python
Classifier: Programming Language :: Python :: 3
Classifier: Programming Language :: Python :: 3.6
Classifier: Programming Language :: Python :: 3.7
Requires-Python: >=3.6
Requires-Dist: olefile (>=0.46)
